LICENCE.txt
MANIFEST.in
README.md
setup.py
prsaw/PRSAW.py
prsaw/__init__.py
prsaw.egg-info/PKG-INFO
prsaw.egg-info/SOURCES.txt
prsaw.egg-info/dependency_links.txt
prsaw.egg-info/requires.txt
prsaw.egg-info/top_level.txt