Metadata-Version: 2.1
Name: prsaw
Version: 0.1.2
Summary: PRSAW, an acronym for `Python Random Stuff API Wrapper`, is a wrapper for the Random Stuff API.
Home-page: https://github.com/CodeWithSwastik/prsaw
Author: Swas.py
Author-email: cwswas.py@gmail.com
License: MIT
Keywords: random stuff,api,wrapper
Platform: UNKNOWN
Classifier: Development Status :: 3 - Alpha
Classifier: Intended Audience :: Developers
Classifier: License :: OSI Approved :: MIT License
Classifier: Programming Language :: Python :: 3
